<?xml version="1.0" encoding="utf-8" ?>
<dwsync>
<file name="action-types.js" server="ftp.rootednsoil.com//public_html/" local="132576335135485497" remote="132575830800000000" Dst="1" />
<file name="actions.js" server="ftp.rootednsoil.com//public_html/" local="132576335139140206" remote="132575830800000000" Dst="1" />
<file name="constants.js" server="ftp.rootednsoil.com//public_html/" local="132576335139509199" remote="132575830800000000" Dst="1" />
<file name="index.js" server="ftp.rootednsoil.com//public_html/" local="132576335141837020" remote="132575830800000000" Dst="1" />
<file name="reducers.js" server="ftp.rootednsoil.com//public_html/" local="132576335144991516" remote="132575830800000000" Dst="1" />
<file name="resolvers.js" server="ftp.rootednsoil.com//public_html/" local="132576335146211522" remote="132575830800000000" Dst="1" />
<file name="selectors.js" server="ftp.rootednsoil.com//public_html/" local="132576335147897528" remote="132575830800000000" Dst="1" />
<file name="utils.js" server="ftp.rootednsoil.com//public_html/" local="132576335158257695" remote="132575830800000000" Dst="1" />
</dwsync>